glicko2/__init__.py
glicko2/glicko2.py
tests/__init__.py
tests/tests.py
glicko2-2.1.0.dist-info/LICENSE
glicko2-2.1.0.dist-info/METADATA
glicko2-2.1.0.dist-info/WHEEL
glicko2-2.1.0.dist-info/top_level.txt
glicko2-2.1.0.dist-info/RECORD
