Metadata-Version: 2.1
Name: glicko2
Version: 2.1.0
Summary: Python implementation of glicko2
Home-page: https://github.com/deepy/glicko2
Author: Alexander Nordlund
Author-email: deep.alexander@gmail.com
Classifier: Programming Language :: Python :: 3
Classifier: Development Status :: 6 - Mature
Classifier: License :: OSI Approved :: MIT License
Classifier: Operating System :: OS Independent
Classifier: Intended Audience :: Developers
Classifier: Intended Audience :: Science/Research
Classifier: Topic :: Scientific/Engineering :: Mathematics
Requires-Python: >=3.7
License-File: LICENSE
